spm1d/__init__.py
spm1d/_plot.py
spm1d/geom.py
spm1d/io.py
spm1d/plot.py
spm1d/util.py
spm1d/data/__init__.py
spm1d/data/_base.py
spm1d/data/datafiles/Besier2009kneeflexion.npz
spm1d/data/datafiles/Besier2009muscleforces.npz
spm1d/data/datafiles/Dorn2012.npz
spm1d/data/datafiles/Neptune1999kneekin.npz
spm1d/data/datafiles/Pataky2014cop.npz
spm1d/data/datafiles/SmallSampleLargePosNegEffects.npy
spm1d/data/datafiles/ex_grf_means.npz
spm1d/data/datafiles/ex_grf_speeds.npy
spm1d/data/datafiles/ex_grf_speeds_cond.npy
spm1d/data/datafiles/ex_grf_subj000.npy
spm1d/data/datafiles/ex_grf_subj001.npy
spm1d/data/datafiles/ex_grf_subj002.npy
spm1d/data/datafiles/ex_grf_subj003.npy
spm1d/data/datafiles/ex_grf_subj004.npy
spm1d/data/datafiles/ex_grf_subj005.npy
spm1d/data/datafiles/ex_grf_subj006.npy
spm1d/data/datafiles/ex_grf_subj007.npy
spm1d/data/datafiles/ex_grf_subj008.npy
spm1d/data/datafiles/ex_grf_subj009.npy
spm1d/data/datafiles/ex_kinematics.npy
spm1d/data/datafiles/ex_kinematics_for_interpolation.npy
spm1d/data/datafiles/ex_sim_twolocalmax.npy
spm1d/data/datafiles/my_spmT.npz
spm1d/data/datafiles/my_spmTi.npz
spm1d/data/datafiles/normality_dataset_A1.npy
spm1d/data/datafiles/normality_dataset_A10.npy
spm1d/data/datafiles/normality_dataset_A11.npy
spm1d/data/datafiles/normality_dataset_A12.npy
spm1d/data/datafiles/normality_dataset_A13.npy
spm1d/data/datafiles/normality_dataset_A14.npy
spm1d/data/datafiles/normality_dataset_A15.npy
spm1d/data/datafiles/normality_dataset_A16.npy
spm1d/data/datafiles/normality_dataset_A17.npy
spm1d/data/datafiles/normality_dataset_A2.npy
spm1d/data/datafiles/normality_dataset_A3.npy
spm1d/data/datafiles/normality_dataset_A4.npy
spm1d/data/datafiles/normality_dataset_A5.npy
spm1d/data/datafiles/normality_dataset_A6.npy
spm1d/data/datafiles/normality_dataset_A7.npy
spm1d/data/datafiles/normality_dataset_A8.npy
spm1d/data/datafiles/normality_dataset_A9.npy
spm1d/data/datafiles/random.npy
spm1d/data/datafiles/random_rough.npy
spm1d-0.4.50.dist-info/licenses/LICENSE.txt
spm1d-0.4.50.dist-info/METADATA
spm1d-0.4.50.dist-info/WHEEL
spm1d-0.4.50.dist-info/top_level.txt
spm1d-0.4.50.dist-info/RECORD
