Metadata-Version: 2.4
Name: spm1d
Version: 0.4.50
Summary: One-Dimensional Statistical Parametric Mapping
Home-page: https://github.com/0todd0000/spm1d
Download-URL: https://github.com/0todd0000/spm1d/archive/master.zip
Author: Todd Pataky
Author-email: spm1d.mail@gmail.com
Keywords: statistics,time series analysis
License-File: LICENSE.txt
Requires-Dist: numpy
Requires-Dist: scipy
Requires-Dist: matplotlib
Dynamic: author
Dynamic: author-email
Dynamic: description
Dynamic: download-url
Dynamic: home-page
Dynamic: keywords
Dynamic: license-file
Dynamic: requires-dist
Dynamic: summary
